macblock/__init__.py
macblock/__main__.py
macblock/blocklists.py
macblock/cli.py
macblock/colors.py
macblock/constants.py
macblock/control.py
macblock/daemon.py
macblock/dns_test.py
macblock/dnsmasq.py
macblock/doctor.py
macblock/errors.py
macblock/exec.py
macblock/fs.py
macblock/help.py
macblock/install.py
macblock/launchd.py
macblock/lists.py
macblock/logs.py
macblock/platform.py
macblock/resolvers.py
macblock/state.py
macblock/status.py
macblock/system_dns.py
macblock/ui.py
macblock/users.py
macblock-0.2.9.dist-info/licenses/LICENSE
macblock-0.2.9.dist-info/METADATA
macblock-0.2.9.dist-info/WHEEL
macblock-0.2.9.dist-info/entry_points.txt
macblock-0.2.9.dist-info/top_level.txt
macblock-0.2.9.dist-info/RECORD
