Metadata-Version: 2.4
Name: macblock
Version: 0.2.9
Summary: Local DNS sinkhole for macOS using dnsmasq
Author: SpyicyDev
License-Expression: MIT
Project-URL: Homepage, https://github.com/SpyicyDev/macblock
Project-URL: Repository, https://github.com/SpyicyDev/macblock
Project-URL: Issues, https://github.com/SpyicyDev/macblock/issues
Project-URL: Changelog, https://github.com/SpyicyDev/macblock/blob/main/CHANGELOG.md
Keywords: dns,ad-blocker,dnsmasq,macos
Classifier: Development Status :: 4 - Beta
Classifier: Environment :: Console
Classifier: Intended Audience :: End Users/Desktop
Classifier: Operating System :: MacOS :: MacOS X
Classifier: Programming Language :: Python :: 3
Classifier: Programming Language :: Python :: 3 :: Only
Classifier: Programming Language :: Python :: 3.10
Classifier: Programming Language :: Python :: 3.11
Classifier: Programming Language :: Python :: 3.12
Classifier: Topic :: Internet :: Name Service (DNS)
Classifier: Topic :: Security
Requires-Python: >=3.10
License-File: LICENSE
Provides-Extra: dev
Requires-Dist: ruff>=0.8.0; extra == "dev"
Requires-Dist: pyright>=1.1.390; extra == "dev"
Requires-Dist: pytest>=8.0.0; extra == "dev"
Requires-Dist: pytest-cov>=5.0.0; extra == "dev"
Dynamic: license-file
